Workbook

Sheet Engagement_Master
A1: Engagement_ID | B1: Client_Name | C1: Service_Line | D1: Engagement_Partner | E1: Contract_Value_INR | F1: Payment_Terms_Days | G1: Start_Date
A2: ENG001 | B2: Arcadia Industries Ltd | C2: Audit | D2: Anil Mehta | E2: 2400000 | F2: 30 | G2: 46143
A3: ENG002 | B3: Bluestone Pharma Pvt Ltd | C3: Tax | D3: Rohit Sharma | E3: 8300000 | F3: 30 | G3: 46130
A4: ENG003 | B4: Crestline Finance Ltd | C4: Consulting | D4: Vikram Iyer | E4: 6000000 | F4: 30 | G4: 46147
A5: ENG004 | B5: Deccan Retail Ltd | C5: Risk Advisory | D5: Sanjay Gupta | E5: 2400000 | F5: 30 | G5: 46140
A6: ENG005 | B6: Everest Infotech Pvt Ltd | C6: Audit | D6: Anil Mehta | E6: 3600000 | F6: 30 | G6: 46116
A7: ENG006 | B7: Fulcrum Motors Ltd | C7: Tax | D7: Rohit Sharma | E7: 7000000 | F7: 30 | G7: 46152
A8: ENG007 | B8: Granite Energy Ltd | C8: Consulting | D8: Vikram Iyer | E8: 9200000 | F8: 60 | G8: 46143
A9: ENG008 | B9: Horizon Foods Pvt Ltd | C9: Risk Advisory | D9: Sanjay Gupta | E9: 9000000 | F9: 45 | G9: 46144
A10: ENG009 | B10: Indus Industries Ltd | C10: Audit | D10: Kavita Rao | E10: 6800000 | F10: 60 | G10: 46118
A11: ENG010 | B11: Jade Pharma Pvt Ltd | C11: Tax | D11: Rohit Sharma | E11: 10300000 | F11: 30 | G11: 46131
A12: ENG011 | B12: Kestrel Finance Ltd | C12: Consulting | D12: Vikram Iyer | E12: 6700000 | F12: 30 | G12: 46127
A13: ENG012 | B13: Lotus Retail Ltd | C13: Risk Advisory | D13: Meera Joshi | E13: 3400000 | F13: 30 | G13: 46150
... A41: ENG040 | B41: Pioneer Foods Pvt Ltd | C41: Risk Advisory | D41: Sanjay Gupta | E41: 7400000 | F41: 30 | G41: 46139

Sheet Invoices
A1: Invoice_No | B1: Engagement_ID | C1: Invoice_Date | D1: Due_Date | E1: Invoice_Amount_INR
A2: INV-26-0153 | B2: ENG038 | C2: 46146 | D2: 46191 | E2: 1103000
A3: INV-26-0102 | B3: ENG026 | C3: 46146 | D3: 46206 | E3: 984000
A4: INV-26-0119 | B4: ENG030 | C4: 46146 | D4: 46176 | E4: 1229000
A5: INV-26-0111 | B5: ENG028 | C5: 46147 | D5: 46207 | E5: 737000
A6: INV-26-0157 | B6: ENG039 | C6: 46148 | D6: 46208 | E6: 739000
A7: INV-26-0140 | B7: ENG035 | C7: 46149 | D7: 46209 | E7: 228000
A8: INV-26-0162 | B8: ENG040 | C8: 46149 | D8: 46179 | E8: 945000
A9: INV-26-0070 | B9: ENG018 | C9: 46149 | D9: 46179 | E9: 1394000
A10: INV-26-0107 | B10: ENG027 | C10: 46150 | D10: 46180 | E10: 783000
A11: INV-26-0034 | B11: ENG009 | C11: 46151 | D11: 46211 | E11: 916000
A12: INV-26-0061 | B12: ENG016 | C12: 46156 | D12: 46186 | E12: 581000
A13: INV-26-0079 | B13: ENG020 | C13: 46156 | D13: 46201 | E13: 490000
... A99: INV-26-0109 | B99: ENG027 | C99: 46223 | D99: 46253 | E99: 516000
A100: INV-26-0121 | B100: ENG030 | C100: 46223 | D100: 46253
A101: INV-26-0003 | B101: ENG001 | C101: 46223 | D101: 46253 | E101: 360000
A102: INV-26-0092 | B102: ENG023 | C102: 46223 | D102: 46283 | E102: 236000
A103: INV-26-0138 | B103: ENG034 | C103: 46225 | D103: 46255 | E103: 1081000
A104: INV-26-0096 | B104: ENG024 | C104: 46226 | D104: 46256 | E104: 616000
A105: INV-26-0048 | B105: ENG012 | C105: 46226 | D105: 46256 | E105: 481000
A106: INV-26-0128 | B106: ENG032 | C106: 46226 | D106: 46256 | E106: 628000
A107: INV-26-0159 | B107: ENG039 | C107: 46227 | D107: 46287 | E107: 723000
A108: INV-26-0150 | B108: ENG037 | C108: 46227 | D108: 46272 | E108: 669000
A109: INV-26-0031 | B109: ENG008 | C109: 46227 | D109: 46272 | E109: 890000
A110: INV-26-0147 | B110: ENG036 | C110: 46229 | D110: 46274 | E110: 1501000
A111: INV-26-0036 | B111: ENG009 | C111: 46229 | D111: 46289 | E111: 655000
A112: INV-26-0076 | B112: ENG019 | C112: 46229 | D112: 46199 | E112: 948000
... A169: INV-26-0101 | B169: ENG025 | C169: 46291 | D169: 46321 | E169: 845000

Sheet Collections
A1: Receipt_ID | B1: Invoice_No | C1: Receipt_Date | D1: Amount_Received_INR | E1: Invoice_Date | F1: Date_Check
A2: RCP-0001 | B2: INV-26-0013 | C2: 46187 | D2: 295000 | E2: {=_xlfn.XLOOKUP(B2,Invoices!$A:$A,Invoices!$C:$C,"NO INVOICE")} -> 46156 | F2: =IF(E2="NO INVOICE","NO INVOICE",IF(C2<E2,"ERROR","OK")) -> OK
A3: RCP-0002 | B3: INV-26-0114 | C3: 46188 | D3: 1129000 | E3: {=_xlfn.XLOOKUP(B3,Invoices!$A:$A,Invoices!$C:$C,"NO INVOICE")} -> 46157 | F3: =IF(E3="NO INVOICE","NO INVOICE",IF(C3<E3,"ERROR","OK")) -> OK
A4: RCP-0003 | B4: INV-26-0136 | C4: 46192 | D4: 1083000 | E4: {=_xlfn.XLOOKUP(B4,Invoices!$A:$A,Invoices!$C:$C,"NO INVOICE")} -> 46159 | F4: =IF(E4="NO INVOICE","NO INVOICE",IF(C4<E4,"ERROR","OK")) -> OK
A5: RCP-0004 | B5: INV-26-0006 | C5: 46195 | D5: 813000 | E5: {=_xlfn.XLOOKUP(B5,Invoices!$A:$A,Invoices!$C:$C,"NO INVOICE")} -> 46161 | F5: =IF(E5="NO INVOICE","NO INVOICE",IF(C5<E5,"ERROR","OK")) -> OK
A6: RCP-0005 | B6: INV-26-0001 | C6: 46196 | D6: 360000 | E6: {=_xlfn.XLOOKUP(B6,Invoices!$A:$A,Invoices!$C:$C,"NO INVOICE")} -> 46156 | F6: =IF(E6="NO INVOICE","NO INVOICE",IF(C6<E6,"ERROR","OK")) -> OK
A7: RCP-0006 | B7: INV-26-0131 | C7: 46198 | D7: 705000 | E7: {=_xlfn.XLOOKUP(B7,Invoices!$A:$A,Invoices!$C:$C,"NO INVOICE")} -> 46165 | F7: =IF(E7="NO INVOICE","NO INVOICE",IF(C7<E7,"ERROR","OK")) -> OK
A8: RCP-0007 | B8: INV-26-0162 | C8: 46198 | D8: 945000 | E8: {=_xlfn.XLOOKUP(B8,Invoices!$A:$A,Invoices!$C:$C,"NO INVOICE")} -> 46149 | F8: =IF(E8="NO INVOICE","NO INVOICE",IF(C8<E8,"ERROR","OK")) -> OK
A9: RCP-0008 | B9: INV-26-0153 | C9: 46200 | D9: 580000 | E9: {=_xlfn.XLOOKUP(B9,Invoices!$A:$A,Invoices!$C:$C,"NO INVOICE")} -> 46146 | F9: =IF(E9="NO INVOICE","NO INVOICE",IF(C9<E9,"ERROR","OK")) -> OK
A10: RCP-0009 | B10: INV-26-0061 | C10: 46200 | D10: 581000 | E10: {=_xlfn.XLOOKUP(B10,Invoices!$A:$A,Invoices!$C:$C,"NO INVOICE")} -> 46156 | F10: =IF(E10="NO INVOICE","NO INVOICE",IF(C10<E10,"ERROR","OK")) -> OK
A11: RCP-0010 | B11: INV-26-0070 | C11: 46200 | D11: 1394000 | E11: {=_xlfn.XLOOKUP(B11,Invoices!$A:$A,Invoices!$C:$C,"NO INVOICE")} -> 46149 | F11: =IF(E11="NO INVOICE","NO INVOICE",IF(C11<E11,"ERROR","OK")) -> OK
A12: RCP-0011 | B12: INV-26-0102 | C12: 46201 | D12: 1234000 | E12: {=_xlfn.XLOOKUP(B12,Invoices!$A:$A,Invoices!$C:$C,"NO INVOICE")} -> 46146 | F12: =IF(E12="NO INVOICE","NO INVOICE",IF(C12<E12,"ERROR","OK")) -> OK
A13: RCP-0012 | B13: INV-26-0079 | C13: 46206 | D13: 263000 | E13: {=_xlfn.XLOOKUP(B13,Invoices!$A:$A,Invoices!$C:$C,"NO INVOICE")} -> 46156 | F13: =IF(E13="NO INVOICE","NO INVOICE",IF(C13<E13,"ERROR","OK")) -> OK
... A97: RCP-0096 | B97: INV-26-9999 | C97: 46283 | D97: 300000 | E97: {=_xlfn.XLOOKUP(B97,Invoices!$A:$A,Invoices!$C:$C,"NO INVOICE")} -> NO INVOICE | F97: =IF(E97="NO INVOICE","NO INVOICE",IF(C97<E97,"ERROR","OK")) -> NO INVOICE

Sheet Headcount
A1: Employee_ID | B1: Service_Line | C1: Grade | D1: Monthly_Cost_INR | E1: Join_Date | F1: Service_Line_Clean | G1: Duplicate_Check
A2: EMP0001 | B2: Audit | C2: Consultant | D2: 98000 | E2: 45648 | F2: =PROPER(TRIM(B2)) -> Audit | G2: =IF(COUNTIF($A$2:A2,A2)>1,"DUPLICATE","OK") -> OK
A3: EMP0002 | B3: Tax | C3: Manager | D3: 237000 | E3: 45455 | F3: =PROPER(TRIM(B3)) -> Tax | G3: =IF(COUNTIF($A$2:A3,A3)>1,"DUPLICATE","OK") -> OK
A4: EMP0003 | B4: Consulting | C4: Consultant | D4: 98000 | E4: 44191 | F4: =PROPER(TRIM(B4)) -> Consulting | G4: =IF(COUNTIF($A$2:A4,A4)>1,"DUPLICATE","OK") -> OK
A5: EMP0004 | B5: Risk Advisory | C5: Analyst | D5: 72000 | E5: 45625 | F5: =PROPER(TRIM(B5)) -> Risk Advisory | G5: =IF(COUNTIF($A$2:A5,A5)>1,"DUPLICATE","OK") -> OK
A6: EMP0005 | B6: Audit | C6: Consultant | D6: 88000 | E6: 43617 | F6: =PROPER(TRIM(B6)) -> Audit | G6: =IF(COUNTIF($A$2:A6,A6)>1,"DUPLICATE","OK") -> OK
A7: EMP0006 | B7: Tax | C7: Manager | D7: 192000 | E7: 43660 | F7: =PROPER(TRIM(B7)) -> Tax | G7: =IF(COUNTIF($A$2:A7,A7)>1,"DUPLICATE","OK") -> OK
A8: EMP0007 | B8: Consulting | C8: Analyst | D8: 64000 | E8: 44782 | F8: =PROPER(TRIM(B8)) -> Consulting | G8: =IF(COUNTIF($A$2:A8,A8)>1,"DUPLICATE","OK") -> OK
A9: EMP0008 | B9: Risk Advisory | C9: Analyst | D9: 71000 | E9: 43933 | F9: =PROPER(TRIM(B9)) -> Risk Advisory | G9: =IF(COUNTIF($A$2:A9,A9)>1,"DUPLICATE","OK") -> OK
A10: EMP0009 | B10: Audit | C10: Analyst | D10: 72000 | E10: 45372 | F10: =PROPER(TRIM(B10)) -> Audit | G10: =IF(COUNTIF($A$2:A10,A10)>1,"DUPLICATE","OK") -> OK
A11: EMP0010 | B11: Tax | C11: Consultant | D11: 89000 | E11: 45778 | F11: =PROPER(TRIM(B11)) -> Tax | G11: =IF(COUNTIF($A$2:A11,A11)>1,"DUPLICATE","OK") -> OK
A12: EMP0011 | B12: Consulting | C12: Senior Consultant | D12: 130000 | E12: 44838 | F12: =PROPER(TRIM(B12)) -> Consulting | G12: =IF(COUNTIF($A$2:A12,A12)>1,"DUPLICATE","OK") -> OK
A13: EMP0012 | B13: Risk Advisory | C13: Director | D13: 437000 | E13: 44451 | F13: =PROPER(TRIM(B13)) -> Risk Advisory | G13: =IF(COUNTIF($A$2:A13,A13)>1,"DUPLICATE","OK") -> OK
... A122: EMP0034 | B122: Tax | C122: Consultant | D122: 88000 | E122: 44812 | F122: =PROPER(TRIM(B122)) -> Tax | G122: =IF(COUNTIF($A$2:A122,A122)>1,"DUPLICATE","OK") -> DUPLICATE

Sheet Control
A1: Report As-Of Date | B1: 46295
A2: Period Start | B2: 46113
A3: Days in Period | B3: =B1-B2+1 -> 183
A4: Months in Period | B4: 6

Sheet Working
A1: Invoice_No | B1: Engagement_ID | C1: Invoice_Date | D1: Due_Date | E1: Invoice_Amount | F1: Client_Name | G1: Service_Line | H1: Partner | I1: Amount_Received | J1: Outstanding | K1: Days_Overdue | L1: Ageing_Bucket | M1: Invoice_Month
A2: =Invoices!A2 -> INV-26-0153 | B2: =Invoices!B2 -> ENG038 | C2: =Invoices!C2 -> 46146 | D2: =Invoices!D2 -> 46191 | E2: =IF(Invoices!E2="","",Invoices!E2) -> 1103000 | F2: {=_xlfn.XLOOKUP(B2,Engagement_Master!$A:$A,Engagement_Master!$B:$B,"NOT FOUND")} -> Nova Motors Ltd | G2: {=_xlfn.XLOOKUP(B2,Engagement_Master!$A:$A,Engagement_Master!$C:$C,"NOT FOUND")} -> Tax | H2: {=_xlfn.XLOOKUP(B2,Engagement_Master!$A:$A,Engagement_Master!$D:$D,"NOT FOUND")} -> Neha Kapoor | I2: =SUMIFS(Collections!$D:$D,Collections!$B:$B,A2) -> 580000 | J2: =IF(E2="","",E2-I2) -> 523000 | K2: =IF(J2="","",IF(J2<=0,0,MAX(0,Control!$B$1-D2))) -> 104 | L2: =IF(J2="","",IF(J2<=0,"Paid",IF(K2=0,"Not Due",IFS(K2<=30,"0-30",K2<=60,"31-60",K2<=90,"61-90",TRUE,"90+")))) -> 90+ | M2: =TEXT(C2,"YYYY-MM") -> 2026-05
A3: =Invoices!A3 -> INV-26-0102 | B3: =Invoices!B3 -> ENG026 | C3: =Invoices!C3 -> 46146 | D3: =Invoices!D3 -> 46206 | E3: =IF(Invoices!E3="","",Invoices!E3) -> 984000 | F3: {=_xlfn.XLOOKUP(B3,Engagement_Master!$A:$A,Engagement_Master!$B:$B,"NOT FOUND")} -> Banyan Pharma Pvt Ltd | G3: {=_xlfn.XLOOKUP(B3,Engagement_Master!$A:$A,Engagement_Master!$C:$C,"NOT FOUND")} -> Tax | H3: {=_xlfn.XLOOKUP(B3,Engagement_Master!$A:$A,Engagement_Master!$D:$D,"NOT FOUND")} -> Neha Kapoor | I3: =SUMIFS(Collections!$D:$D,Collections!$B:$B,A3) -> 1234000 | J3: =IF(E3="","",E3-I3) -> -250000 | K3: =IF(J3="","",IF(J3<=0,0,MAX(0,Control!$B$1-D3))) -> 0 | L3: =IF(J3="","",IF(J3<=0,"Paid",IF(K3=0,"Not Due",IFS(K3<=30,"0-30",K3<=60,"31-60",K3<=90,"61-90",TRUE,"90+")))) -> Paid | M3: =TEXT(C3,"YYYY-MM") -> 2026-05
A4: =Invoices!A4 -> INV-26-0119 | B4: =Invoices!B4 -> ENG030 | C4: =Invoices!C4 -> 46146 | D4: =Invoices!D4 -> 46176 | E4: =IF(Invoices!E4="","",Invoices!E4) -> 1229000 | F4: {=_xlfn.XLOOKUP(B4,Engagement_Master!$A:$A,Engagement_Master!$B:$B,"NOT FOUND")} -> Falcon Motors Ltd | G4: {=_xlfn.XLOOKUP(B4,Engagement_Master!$A:$A,Engagement_Master!$C:$C,"NOT FOUND")} -> Tax | H4: {=_xlfn.XLOOKUP(B4,Engagement_Master!$A:$A,Engagement_Master!$D:$D,"NOT FOUND")} -> Neha Kapoor | I4: =SUMIFS(Collections!$D:$D,Collections!$B:$B,A4) -> 1229000 | J4: =IF(E4="","",E4-I4) -> 0 | K4: =IF(J4="","",IF(J4<=0,0,MAX(0,Control!$B$1-D4))) -> 0 | L4: =IF(J4="","",IF(J4<=0,"Paid",IF(K4=0,"Not Due",IFS(K4<=30,"0-30",K4<=60,"31-60",K4<=90,"61-90",TRUE,"90+")))) -> Paid | M4: =TEXT(C4,"YYYY-MM") -> 2026-05
A5: =Invoices!A5 -> INV-26-0111 | B5: =Invoices!B5 -> ENG028 | C5: =Invoices!C5 -> 46147 | D5: =Invoices!D5 -> 46207 | E5: =IF(Invoices!E5="","",Invoices!E5) -> 737000 | F5: {=_xlfn.XLOOKUP(B5,Engagement_Master!$A:$A,Engagement_Master!$B:$B,"NOT FOUND")} -> Delta Retail Ltd | G5: {=_xlfn.XLOOKUP(B5,Engagement_Master!$A:$A,Engagement_Master!$C:$C,"NOT FOUND")} -> Risk Advisory | H5: {=_xlfn.XLOOKUP(B5,Engagement_Master!$A:$A,Engagement_Master!$D:$D,"NOT FOUND")} -> Meera Joshi | I5: =SUMIFS(Collections!$D:$D,Collections!$B:$B,A5) -> 339000 | J5: =IF(E5="","",E5-I5) -> 398000 | K5: =IF(J5="","",IF(J5<=0,0,MAX(0,Control!$B$1-D5))) -> 88 | L5: =IF(J5="","",IF(J5<=0,"Paid",IF(K5=0,"Not Due",IFS(K5<=30,"0-30",K5<=60,"31-60",K5<=90,"61-90",TRUE,"90+")))) -> 61-90 | M5: =TEXT(C5,"YYYY-MM") -> 2026-05
A6: =Invoices!A6 -> INV-26-0157 | B6: =Invoices!B6 -> ENG039 | C6: =Invoices!C6 -> 46148 | D6: =Invoices!D6 -> 46208 | E6: =IF(Invoices!E6="","",Invoices!E6) -> 739000 | F6: {=_xlfn.XLOOKUP(B6,Engagement_Master!$A:$A,Engagement_Master!$B:$B,"NOT FOUND")} -> Opal Energy Ltd | G6: {=_xlfn.XLOOKUP(B6,Engagement_Master!$A:$A,Engagement_Master!$C:$C,"NOT FOUND")} -> Consulting | H6: {=_xlfn.XLOOKUP(B6,Engagement_Master!$A:$A,Engagement_Master!$D:$D,"NOT FOUND")} -> Vikram Iyer | I6: =SUMIFS(Collections!$D:$D,Collections!$B:$B,A6) -> 739000 | J6: =IF(E6="","",E6-I6) -> 0 | K6: =IF(J6="","",IF(J6<=0,0,MAX(0,Control!$B$1-D6))) -> 0 | L6: =IF(J6="","",IF(J6<=0,"Paid",IF(K6=0,"Not Due",IFS(K6<=30,"0-30",K6<=60,"31-60",K6<=90,"61-90",TRUE,"90+")))) -> Paid | M6: =TEXT(C6,"YYYY-MM") -> 2026-05
A7: =Invoices!A7 -> INV-26-0140 | B7: =Invoices!B7 -> ENG035 | C7: =Invoices!C7 -> 46149 | D7: =Invoices!D7 -> 46209 | E7: =IF(Invoices!E7="","",Invoices!E7) -> 228000 | F7: {=_xlfn.XLOOKUP(B7,Engagement_Master!$A:$A,Engagement_Master!$B:$B,"NOT FOUND")} -> Krypton Finance Ltd | G7: {=_xlfn.XLOOKUP(B7,Engagement_Master!$A:$A,Engagement_Master!$C:$C,"NOT FOUND")} -> Consulting | H7: {=_xlfn.XLOOKUP(B7,Engagement_Master!$A:$A,Engagement_Master!$D:$D,"NOT FOUND")} -> Priya Nair | I7: =SUMIFS(Collections!$D:$D,Collections!$B:$B,A7) -> 0 | J7: =IF(E7="","",E7-I7) -> 228000 | K7: =IF(J7="","",IF(J7<=0,0,MAX(0,Control!$B$1-D7))) -> 86 | L7: =IF(J7="","",IF(J7<=0,"Paid",IF(K7=0,"Not Due",IFS(K7<=30,"0-30",K7<=60,"31-60",K7<=90,"61-90",TRUE,"90+")))) -> 61-90 | M7: =TEXT(C7,"YYYY-MM") -> 2026-05
A8: =Invoices!A8 -> INV-26-0162 | B8: =Invoices!B8 -> ENG040 | C8: =Invoices!C8 -> 46149 | D8: =Invoices!D8 -> 46179 | E8: =IF(Invoices!E8="","",Invoices!E8) -> 945000 | F8: {=_xlfn.XLOOKUP(B8,Engagement_Master!$A:$A,Engagement_Master!$B:$B,"NOT FOUND")} -> Pioneer Foods Pvt Ltd | G8: {=_xlfn.XLOOKUP(B8,Engagement_Master!$A:$A,Engagement_Master!$C:$C,"NOT FOUND")} -> Risk Advisory | H8: {=_xlfn.XLOOKUP(B8,Engagement_Master!$A:$A,Engagement_Master!$D:$D,"NOT FOUND")} -> Sanjay Gupta | I8: =SUMIFS(Collections!$D:$D,Collections!$B:$B,A8) -> 945000 | J8: =IF(E8="","",E8-I8) -> 0 | K8: =IF(J8="","",IF(J8<=0,0,MAX(0,Control!$B$1-D8))) -> 0 | L8: =IF(J8="","",IF(J8<=0,"Paid",IF(K8=0,"Not Due",IFS(K8<=30,"0-30",K8<=60,"31-60",K8<=90,"61-90",TRUE,"90+")))) -> Paid | M8: =TEXT(C8,"YYYY-MM") -> 2026-05
A9: =Invoices!A9 -> INV-26-0070 | B9: =Invoices!B9 -> ENG018 | C9: =Invoices!C9 -> 46149 | D9: =Invoices!D9 -> 46179 | E9: =IF(Invoices!E9="","",Invoices!E9) -> 1394000 | F9: {=_xlfn.XLOOKUP(B9,Engagement_Master!$A:$A,Engagement_Master!$B:$B,"NOT FOUND")} -> Redwood Pharma Pvt Ltd | G9: {=_xlfn.XLOOKUP(B9,Engagement_Master!$A:$A,Engagement_Master!$C:$C,"NOT FOUND")} -> Tax | H9: {=_xlfn.XLOOKUP(B9,Engagement_Master!$A:$A,Engagement_Master!$D:$D,"NOT FOUND")} -> Neha Kapoor | I9: =SUMIFS(Collections!$D:$D,Collections!$B:$B,A9) -> 1394000 | J9: =IF(E9="","",E9-I9) -> 0 | K9: =IF(J9="","",IF(J9<=0,0,MAX(0,Control!$B$1-D9))) -> 0 | L9: =IF(J9="","",IF(J9<=0,"Paid",IF(K9=0,"Not Due",IFS(K9<=30,"0-30",K9<=60,"31-60",K9<=90,"61-90",TRUE,"90+")))) -> Paid | M9: =TEXT(C9,"YYYY-MM") -> 2026-05
A10: =Invoices!A10 -> INV-26-0107 | B10: =Invoices!B10 -> ENG027 | C10: =Invoices!C10 -> 46150 | D10: =Invoices!D10 -> 46180 | E10: =IF(Invoices!E10="","",Invoices!E10) -> 783000 | F10: {=_xlfn.XLOOKUP(B10,Engagement_Master!$A:$A,Engagement_Master!$B:$B,"NOT FOUND")} -> Cobalt Finance Ltd | G10: {=_xlfn.XLOOKUP(B10,Engagement_Master!$A:$A,Engagement_Master!$C:$C,"NOT FOUND")} -> Consulting | H10: {=_xlfn.XLOOKUP(B10,Engagement_Master!$A:$A,Engagement_Master!$D:$D,"NOT FOUND")} -> Priya Nair | I10: =SUMIFS(Collections!$D:$D,Collections!$B:$B,A10) -> 783000 | J10: =IF(E10="","",E10-I10) -> 0 | K10: =IF(J10="","",IF(J10<=0,0,MAX(0,Control!$B$1-D10))) -> 0 | L10: =IF(J10="","",IF(J10<=0,"Paid",IF(K10=0,"Not Due",IFS(K10<=30,"0-30",K10<=60,"31-60",K10<=90,"61-90",TRUE,"90+")))) -> Paid | M10: =TEXT(C10,"YYYY-MM") -> 2026-05
A11: =Invoices!A11 -> INV-26-0034 | B11: =Invoices!B11 -> ENG009 | C11: =Invoices!C11 -> 46151 | D11: =Invoices!D11 -> 46211 | E11: =IF(Invoices!E11="","",Invoices!E11) -> 916000 | F11: {=_xlfn.XLOOKUP(B11,Engagement_Master!$A:$A,Engagement_Master!$B:$B,"NOT FOUND")} -> Indus Industries Ltd | G11: {=_xlfn.XLOOKUP(B11,Engagement_Master!$A:$A,Engagement_Master!$C:$C,"NOT FOUND")} -> Audit | H11: {=_xlfn.XLOOKUP(B11,Engagement_Master!$A:$A,Engagement_Master!$D:$D,"NOT FOUND")} -> Kavita Rao | I11: =SUMIFS(Collections!$D:$D,Collections!$B:$B,A11) -> 916000 | J11: =IF(E11="","",E11-I11) -> 0 | K11: =IF(J11="","",IF(J11<=0,0,MAX(0,Control!$B$1-D11))) -> 0 | L11: =IF(J11="","",IF(J11<=0,"Paid",IF(K11=0,"Not Due",IFS(K11<=30,"0-30",K11<=60,"31-60",K11<=90,"61-90",TRUE,"90+")))) -> Paid | M11: =TEXT(C11,"YYYY-MM") -> 2026-05
A12: =Invoices!A12 -> INV-26-0061 | B12: =Invoices!B12 -> ENG016 | C12: =Invoices!C12 -> 46156 | D12: =Invoices!D12 -> 46186 | E12: =IF(Invoices!E12="","",Invoices!E12) -> 581000 | F12: {=_xlfn.XLOOKUP(B12,Engagement_Master!$A:$A,Engagement_Master!$B:$B,"NOT FOUND")} -> Pinnacle Foods Pvt Ltd | G12: {=_xlfn.XLOOKUP(B12,Engagement_Master!$A:$A,Engagement_Master!$C:$C,"NOT FOUND")} -> Risk Advisory | H12: {=_xlfn.XLOOKUP(B12,Engagement_Master!$A:$A,Engagement_Master!$D:$D,"NOT FOUND")} -> Sanjay Gupta | I12: =SUMIFS(Collections!$D:$D,Collections!$B:$B,A12) -> 581000 | J12: =IF(E12="","",E12-I12) -> 0 | K12: =IF(J12="","",IF(J12<=0,0,MAX(0,Control!$B$1-D12))) -> 0 | L12: =IF(J12="","",IF(J12<=0,"Paid",IF(K12=0,"Not Due",IFS(K12<=30,"0-30",K12<=60,"31-60",K12<=90,"61-90",TRUE,"90+")))) -> Paid | M12: =TEXT(C12,"YYYY-MM") -> 2026-05
A13: =Invoices!A13 -> INV-26-0079 | B13: =Invoices!B13 -> ENG020 | C13: =Invoices!C13 -> 46156 | D13: =Invoices!D13 -> 46201 | E13: =IF(Invoices!E13="","",Invoices!E13) -> 490000 | F13: {=_xlfn.XLOOKUP(B13,Engagement_Master!$A:$A,Engagement_Master!$B:$B,"NOT FOUND")} -> Terra Retail Ltd | G13: {=_xlfn.XLOOKUP(B13,Engagement_Master!$A:$A,Engagement_Master!$C:$C,"NOT FOUND")} -> Risk Advisory | H13: {=_xlfn.XLOOKUP(B13,Engagement_Master!$A:$A,Engagement_Master!$D:$D,"NOT FOUND")} -> Meera Joshi | I13: =SUMIFS(Collections!$D:$D,Collections!$B:$B,A13) -> 263000 | J13: =IF(E13="","",E13-I13) -> 227000 | K13: =IF(J13="","",IF(J13<=0,0,MAX(0,Control!$B$1-D13))) -> 94 | L13: =IF(J13="","",IF(J13<=0,"Paid",IF(K13=0,"Not Due",IFS(K13<=30,"0-30",K13<=60,"31-60",K13<=90,"61-90",TRUE,"90+")))) -> 90+ | M13: =TEXT(C13,"YYYY-MM") -> 2026-05
... A169: =Invoices!A169 -> INV-26-0101 | B169: =Invoices!B169 -> ENG025 | C169: =Invoices!C169 -> 46291 | D169: =Invoices!D169 -> 46321 | E169: =IF(Invoices!E169="","",Invoices!E169) -> 845000 | F169: {=_xlfn.XLOOKUP(B169,Engagement_Master!$A:$A,Engagement_Master!$B:$B,"NOT FOUND")} -> Aurora Industries Ltd | G169: {=_xlfn.XLOOKUP(B169,Engagement_Master!$A:$A,Engagement_Master!$C:$C,"NOT FOUND")} -> Audit | H169: {=_xlfn.XLOOKUP(B169,Engagement_Master!$A:$A,Engagement_Master!$D:$D,"NOT FOUND")} -> Anil Mehta | I169: =SUMIFS(Collections!$D:$D,Collections!$B:$B,A169) -> 0 | J169: =IF(E169="","",E169-I169) -> 845000 | K169: =IF(J169="","",IF(J169<=0,0,MAX(0,Control!$B$1-D169))) -> 0 | L169: =IF(J169="","",IF(J169<=0,"Paid",IF(K169=0,"Not Due",IFS(K169<=30,"0-30",K169<=60,"31-60",K169<=90,"61-90",TRUE,"90+")))) -> Not Due | M169: =TEXT(C169,"YYYY-MM") -> 2026-09

Sheet PV_Ageing

Sheet PV_Ageing_Values
A1: SUM of Outstanding | B1: Ageing_Bucket
A2: Service_Line | B2: 0-30 | C2: 31-60 | D2: 61-90 | E2: 90+ | F2: Not Due | G2: Grand Total
A3: Audit | B3: 3937000 | C3: 3109000 | D3: 397000 | E3: 466000 | F3: 5199000 | G3: 13108000
A4: Consulting | B4: 6968000 | C4: 4647000 | D4: 1900000 | E4: 948000 | F4: 11465000 | G4: 25928000
A5: NOT FOUND | B5: 450000 | G5: 450000
A6: Risk Advisory | B6: 3396000 | C6: 1157000 | D6: 781000 | E6: 227000 | F6: 3676000 | G6: 9237000
A7: Tax | B7: 960000 | C7: 1967000 | D7: 1349000 | E7: 523000 | F7: 6382000 | G7: 11181000
A8: Grand Total | B8: 15711000 | C8: 10880000 | D8: 4427000 | E8: 2164000 | F8: 26722000 | G8: 59904000

Sheet PV_Bill_vs_Collect

Sheet PV_Bill_vs_Collect_Values
A1: Service_Line | B1: SUM of Invoice_Amount | C1: SUM of Amount_Received | D1: SUM of Outstanding
A2: Audit | B2: 29032000 | C2: 15924000 | D2: 13108000
A3: Consulting | B3: 36412000 | C3: 10484000 | D3: 25928000
A4: NOT FOUND | B4: 450000 | C4: 0 | D4: 450000
A5: Risk Advisory | B5: 28896000 | C5: 19659000 | D5: 9237000
A6: Tax | B6: 39019000 | C6: 31724000 | D6: 8435000
A7: Grand Total | B7: 133809000 | C7: 77791000 | D7: 57158000

Sheet PV_Top_Overdue

Sheet PV_Top_Overdue_Values
A1: Client_Name | B1: SUM of Outstanding
A2: Granite Energy Ltd | B2: 1263000
A3: Saffron Finance Ltd | B3: 948000
A4: Everest Infotech Pvt Ltd | B4: 863000
A5: Fulcrum Motors Ltd | B5: 643000
A6: Nova Motors Ltd | B6: 523000
A7: Glacier Energy Ltd | B7: 409000
A8: Delta Retail Ltd | B8: 398000
A9: Vertex Motors Ltd | B9: 384000
A10: Harbor Foods Pvt Ltd | B10: 383000
A11: Nimbus Motors Ltd | B11: 322000
A12: Krypton Finance Ltd | B12: 228000
A13: Terra Retail Ltd | B13: 227000
A14: Grand Total | B14: 6591000

Sheet KPI
A1: Total Billed | B1: =SUM(Working!E2:E169) -> 133809000
A2: Total Collected | B2: =SUM(Working!I2:I169) -> 77791000
A3: Total Outstanding | B3: =SUM(Working!J2:J169) -> 57158000
A4: Collection Efficiency % | B4: =B2/B1 -> 0.5813585
A5: Overdue 90+ Amount | B5: =SUMIFS(Working!J2:J169,Working!L2:L169,"90+") -> 2164000
A6: % of Outstanding in 90+ | B6: =B5/B3 -> 0.037859967
A7: DSO (days) | B7: =B3/B1*Control!B3 -> 78.170482
A10: Service_Line | B10: Billed | C10: Collected | D10: Outstanding | E10: 90+ | F10: Efficiency % | G10: DSO | H10: Headcount | I10: Billing per Head | J10: People Cost (6M) | K10: Billing ÷ Cost
A11: Audit | B11: =SUMIFS(Working!$E$2:$E$169,Working!$G$2:$G$169,A11) -> 29032000 | C11: =SUMIFS(Working!$I$2:$I$169,Working!$G$2:$G$169,A11) -> 15924000 | D11: =SUMIFS(Working!$J$2:$J$169,Working!$G$2:$G$169,A11) -> 13108000 | E11: =SUMIFS(Working!$J$2:$J$169,Working!$G$2:$G$169,A11,Working!$L$2:$L$169,"90+") -> 466000 | F11: =C11/B11 -> 0.54849821 | G11: =D11/B11*Control!$B$3 -> 82.624828 | H11: =COUNTIFS(Headcount!$F$2:$F$122,A11,Headcount!$G$2:$G$122,"OK") -> 30 | I11: =B11/H11 -> 967733.33 | J11: =SUMIFS(Headcount!$D$2:$D$122,Headcount!$F$2:$F$122,A11,Headcount!$G$2:$G$122,"OK")*Control!$B$4 -> 23340000 | K11: =B11/J11 -> 1.2438732
A12: Consulting | B12: =SUMIFS(Working!$E$2:$E$169,Working!$G$2:$G$169,A12) -> 36412000 | C12: =SUMIFS(Working!$I$2:$I$169,Working!$G$2:$G$169,A12) -> 10484000 | D12: =SUMIFS(Working!$J$2:$J$169,Working!$G$2:$G$169,A12) -> 25928000 | E12: =SUMIFS(Working!$J$2:$J$169,Working!$G$2:$G$169,A12,Working!$L$2:$L$169,"90+") -> 948000 | F12: =C12/B12 -> 0.28792706 | G12: =D12/B12*Control!$B$3 -> 130.30935 | H12: =COUNTIFS(Headcount!$F$2:$F$122,A12,Headcount!$G$2:$G$122,"OK") -> 30 | I12: =B12/H12 -> 1213733.3 | J12: =SUMIFS(Headcount!$D$2:$D$122,Headcount!$F$2:$F$122,A12,Headcount!$G$2:$G$122,"OK")*Control!$B$4 -> 28716000 | K12: =B12/J12 -> 1.2680039
A13: Risk Advisory | B13: =SUMIFS(Working!$E$2:$E$169,Working!$G$2:$G$169,A13) -> 28896000 | C13: =SUMIFS(Working!$I$2:$I$169,Working!$G$2:$G$169,A13) -> 19659000 | D13: =SUMIFS(Working!$J$2:$J$169,Working!$G$2:$G$169,A13) -> 9237000 | E13: =SUMIFS(Working!$J$2:$J$169,Working!$G$2:$G$169,A13,Working!$L$2:$L$169,"90+") -> 227000 | F13: =C13/B13 -> 0.68033638 | G13: =D13/B13*Control!$B$3 -> 58.498443 | H13: =COUNTIFS(Headcount!$F$2:$F$122,A13,Headcount!$G$2:$G$122,"OK") -> 30 | I13: =B13/H13 -> 963200 | J13: =SUMIFS(Headcount!$D$2:$D$122,Headcount!$F$2:$F$122,A13,Headcount!$G$2:$G$122,"OK")*Control!$B$4 -> 24024000 | K13: =B13/J13 -> 1.2027972
A14: Tax | B14: =SUMIFS(Working!$E$2:$E$169,Working!$G$2:$G$169,A14) -> 39019000 | C14: =SUMIFS(Working!$I$2:$I$169,Working!$G$2:$G$169,A14) -> 31724000 | D14: =SUMIFS(Working!$J$2:$J$169,Working!$G$2:$G$169,A14) -> 8435000 | E14: =SUMIFS(Working!$J$2:$J$169,Working!$G$2:$G$169,A14,Working!$L$2:$L$169,"90+") -> 523000 | F14: =C14/B14 -> 0.8130398 | G14: =D14/B14*Control!$B$3 -> 39.560342 | H14: =COUNTIFS(Headcount!$F$2:$F$122,A14,Headcount!$G$2:$G$122,"OK") -> 30 | I14: =B14/H14 -> 1300633.3 | J14: =SUMIFS(Headcount!$D$2:$D$122,Headcount!$F$2:$F$122,A14,Headcount!$G$2:$G$122,"OK")*Control!$B$4 -> 23472000 | K14: =B14/J14 -> 1.6623637

Sheet Test_Cases
A1: TC_ID | B1: Test Scenario | C1: Actual Result | D1: Expected Result | E1: Status | F1: Bug_ID
A2: TC01 | B2: Working total matches Invoices total | C2: =SUM(Working!E2:E169)=SUM(Invoices!E2:E169) -> TRUE | D2: TRUE | E2: =IF(C2=D2,"PASS","FAIL") -> PASS
A3: TC02 | B3: No duplicate invoice numbers | C3: =SUMPRODUCT((COUNTIF(Invoices!A2:A169,Invoices!A2:A169)>1)*1) -> 2 | D3: 0 | E3: =IF(C3=D3,"PASS","FAIL") -> FAIL | F3: BUG-01
A4: TC03 | B4: Every invoice maps to an engagement | C4: =COUNTIF(Working!F2:F169,"NOT FOUND") -> 1 | D4: 0 | E4: =IF(C4=D4,"PASS","FAIL") -> FAIL | F4: BUG-02
A5: TC04 | B5: No negative invoice amounts | C5: =COUNTIF(Invoices!E2:E169,"<0") -> 1 | D5: 0 | E5: =IF(C5=D5,"PASS","FAIL") -> FAIL | F5: BUG-03
A6: TC05 | B6: No blank invoice amounts | C6: =COUNTBLANK(Invoices!E2:E169) -> 1 | D6: 0 | E6: =IF(C6=D6,"PASS","FAIL") -> FAIL | F6: BUG-04
A7: TC06 | B7: Due date is not before invoice date | C7: =SUMPRODUCT((Invoices!D2:D169<Invoices!C2:C169)*1) -> 1 | D7: 0 | E7: =IF(C7=D7,"PASS","FAIL") -> FAIL | F7: BUG-05
A8: TC07 | B8: Outstanding is never negative | C8: =COUNTIF(Working!J2:J169,"<0") -> 2 | D8: 0 | E8: =IF(C8=D8,"PASS","FAIL") -> FAIL | F8: BUG-06
A9: TC08 | B9: Every receipt matches a real invoice | C9: =COUNTIF(Collections!F2:F97,"NO INVOICE") -> 1 | D9: 0 | E9: =IF(C9=D9,"PASS","FAIL") -> FAIL | F9: BUG-07
A10: TC09 | B10: Receipt is not dated before its invoice | C10: =COUNTIF(Collections!F2:F97,"ERROR") -> 1 | D10: 0 | E10: =IF(C10=D10,"PASS","FAIL") -> FAIL | F10: BUG-08
A11: TC10 | B11: No duplicate employees | C11: =COUNTIF(Headcount!G2:G122,"DUPLICATE") -> 1 | D11: 0 | E11: =IF(C11=D11,"PASS","FAIL") -> FAIL | F11: BUG-09
A12: TC11 | B12: Cleaned service lines are all valid | C12: =SUMPRODUCT((COUNTIF(Engagement_Master!C2:C41,Headcount!F2:F122)=0)*1) -> 0 | D12: 0 | E12: =IF(C12=D12,"PASS","FAIL") -> PASS | F12: BUG-10
A13: TC12 | B13: Service-line totals + unmapped = total billed | C13: =SUM(KPI!B11:B14)+SUMIFS(Working!E2:E169,Working!F2:F169,"NOT FOUND")=KPI!B1 -> TRUE | D13: TRUE | E13: =IF(C13=D13,"PASS","FAIL") -> PASS

Sheet Monthly_Log
A1: Run Time | B1: As-Of Date | C1: Total Billed | D1: Total Collected | E1: Total Outstanding | F1: DSO (days) | G1: 90+ Amount | H1: Invoices 90+ | I1: Tests Failed
A2: 46294.804 | B2: 46295 | C2: 133809000 | D2: 77791000 | E2: 57158000 | F2: 78 | G2: 2164000 | H2: 4 | I2: 9

Sheet Bug_Log
A1: Bug_ID | B1: TC_ID | C1: What's wrong | D1: Record(s) | E1: Severity | F1: Impact on report | G1: Recommended fix | H1: Status
A2: BUG-01 | B2: TC02 | C2: Same invoice entered twice | D2: INV-26-0018 | E2: High | F2: Billing overstated; its receipt counted twice | G2: Confirm with Billing, remove duplicate | H2: Open
A3: BUG-02 | B3: TC03 | C3: Invoice linked to engagement not in master | D3: INV-26-0167 (ENG045) | E3: High | F3: ₹4,50,000 not assigned to any service line | G3: Confirm correct engagement ID with Finance | H3: Open
A4: BUG-03 | B4: TC04 | C4: Negative invoice with no credit-note label | D4: INV-26-0041 | E4: High | F4: Billing understated; hides in "Paid" in ageing | G4: Check if credit note; record separately | H4: Open
A5: BUG-04 | B5: TC05 | C5: Invoice amount is blank | D5: INV-26-0121 | E5: High | F5: ₹11,40,000 received against an invoice with no amount | G5: Get amount from billing system | H5: Open
A6: BUG-05 | B6: TC06 | C6: Due date earlier than invoice date | D6: INV-26-0076 | E6: Medium | F6: Wrong days overdue and ageing bucket | G6: Recalculate due date from payment terms | H6: Open
A7: BUG-06 | B7: TC07 | C7: Client paid more than invoice amount | D7: RCP-0011 / INV-26-0102 | E7: High | F7: ₹2,50,000 overpaid; possible refund due | G7: Verify with Collections; refund or adjust | H7: Open
A8: BUG-07 | B8: TC08 | C8: Payment against invoice that doesn't exist | D8: RCP-0096 / INV-26-9999 | E8: High | F8: ₹3,00,000 cash received but not matched | G8: Identify correct invoice with client | H8: Open
A9: BUG-08 | B9: TC09 | C9: Payment dated before invoice was sent | D9: RCP-0031 / INV-26-0071 | E9: Medium | F9: Collection timing wrong | G9: Verify date against bank statement | H9: Open
A10: BUG-09 | B10: TC10 | C10: Same employee listed twice | D10: EMP0034 | E10: Medium | F10: Headcount and people cost would be overstated | G10: Excluded via Duplicate_Check; fix in HR source | H10: Handled in MIS
A11: BUG-10 | B11: TC11 | C11: Service line typed inconsistently | D11: EMP0059, EMP0092 | E11: Low | F11: Would miscount headcount per team | G11: Cleaned with TRIM/PROPER; standardise in HR system | H11: Handled in MIS
